MANIFEST.in
requirements.txt
setup.py
delay/__init__.py
delay/socket.py
delay.egg-info/PKG-INFO
delay.egg-info/SOURCES.txt
delay.egg-info/dependency_links.txt
delay.egg-info/requires.txt
delay.egg-info/top_level.txt