Metadata-Version: 1.0
Name: delay
Version: 0.0.4
Summary: A micro library focused on providing wait states in distributed systems
Home-page: https://github.com/Carbyne-Solutions/delay
Author: Matt Daue
Author-email: mdaue@carbyne.solutions
License: BSD-3-Clause
Keywords: distributed system wait-state
Platform: UNKNOWN
